{
  "characters": [
    {
      "character_id": "nate_lazar",
      "age_at_story_start": 34,
      "physical_details": "Occupies Dominic Altieri's 31-year-old body from Chapter 1: 5'10\", dark brown hair, crooked nose, medium build, scar across the left knuckle. Nate's original 2025 body was thinner and wore glasses.",
      "key_relationships": {
        "dominic_altieri": "dead predecessor he overwrote",
        "sarah_chen": "girlfriend under false identity",
        "mort_lazar": "father; knows him as Dom",
        "linda_lazar": "mother; knows him as Dom",
        "victor_kassos": "boss",
        "ray_dunlap": "coworker covering for him",
        "tommy_altieri": "Dominic's brother; financial dependent",
        "renata_altieri": "Dominic's mother; family obligation",
        "gail_ruiz": "diner owner and lunch regular contact"
      },
      "occupation_status": "2025: divorced remote tech-support worker with no children. 2005 as Dominic: Project Coordinator at Kassos Development.",
      "aliases": [
        "Dom",
        "Dominic",
        "Dominic Altieri"
      ],
      "literacy_languages": "English. Technically literate, but has no access to Dominic's memories.",
      "state_transitions": [
        {
          "chapter": "chapter_01",
          "change": "Overwrites Dominic at 3:47 AM on July 11, 2005."
        },
        {
          "chapter": "chapter_11",
          "change": "Learns Dominic had tried to protect Eastbridge tenants, including Mort."
        },
        {
          "chapter": "chapter_15",
          "change": "Drains Dominic's checking and savings to write Tommy a 3,000-dollar check."
        },
        {
          "chapter": "chapter_16",
          "change": "Signs the Eastbridge final closeout packet."
        },
        {
          "chapter": "chapter_17",
          "change": "Takes a left-hand threaded screw from the Lazar's Hardware rubble."
        },
        {
          "chapter": "chapter_18",
          "change": "Starts routing small jobs and customers to Mort's garage operation and keeps showing up weekly."
        }
      ],
      "availability": "All chapters."
    },
    {
      "character_id": "dominic_altieri",
      "age_at_story_start": 31,
      "physical_details": "5'10\", dark hair, crooked nose, medium build, scar across left knuckle. Present only through the body Nate wears, his mail, and memory.",
      "key_relationships": {
        "sarah_chen": "live-in boyfriend of about four years",
        "victor_kassos": "protege and employee",
        "ray_dunlap": "closest work friend",
        "renata_altieri": "son",
        "tommy_altieri": "habitual bailout source",
        "mort_lazar": "Eastbridge tenant Dominic argued to protect"
      },
      "occupation_status": "Project Coordinator at Kassos Development, handling tenant communication, permits, and project follow-through.",
      "aliases": [
        "Dom"
      ],
      "literacy_languages": "English. Fluent in development paperwork and office politics.",
      "state_transitions": [
        {
          "chapter": "chapter_01",
          "change": "Overwritten by Nate and ceases to exist as an active person."
        }
      ],
      "availability": "Dead before the main action."
    },
    {
      "character_id": "sarah_chen",
      "age_at_story_start": 28,
      "physical_details": "Chinese-American history teacher with dark hair, practical clothes, pens, papers, and school routines always in reach.",
      "key_relationships": {
        "nate_lazar": "believes he is Dominic at first; later knows he is profoundly changed",
        "dominic_altieri": "original boyfriend",
        "renata_altieri": "warm but complicated",
        "tommy_altieri": "understands his bailout pattern"
      },
      "occupation_status": "Bridgeport high-school history teacher; teaches summer school in July and returns to full school-year work after winter break.",
      "aliases": [],
      "literacy_languages": "English.",
      "state_transitions": [
        {
          "chapter": "chapter_05",
          "change": "Reads 'Dom' as softer and more present, even as the first shared-memory gap appears."
        },
        {
          "chapter": "chapter_10",
          "change": "Moves from mood-based concern to factual suspicion after Marco, Cape Cod, and client-memory failures."
        },
        {
          "chapter": "chapter_12",
          "change": "Confronts him directly and sleeps on the couch."
        },
        {
          "chapter": "chapter_18",
          "change": "Stops testing old Dominic memories and relates to the changed man in front of her."
        }
      ],
      "availability": "Present from Chapter 1 onward."
    },
    {
      "character_id": "victor_kassos",
      "age_at_story_start": 55,
      "physical_details": "Greek-American, silver-gray hair, tanned, well-tailored, physically controlled rather than large.",
      "key_relationships": {
        "dominic_altieri": "useful protege who handled people well",
        "nate_lazar": "employee becoming unreliable on Eastbridge",
        "ray_dunlap": "reliable lieutenant"
      },
      "occupation_status": "Owner of Kassos Development and a node in the lender-contractor-council network behind Eastbridge.",
      "aliases": [
        "Vic"
      ],
      "literacy_languages": "English, some Greek.",
      "state_transitions": [
        {
          "chapter": "chapter_09",
          "change": "Starts treating Dominic as a competence problem."
        },
        {
          "chapter": "chapter_14",
          "change": "Explains full-clearance financing, Dreher's network, and year-end draws lock Eastbridge, then warns Nate to stop pushing."
        },
        {
          "chapter": "chapter_16",
          "change": "Requires signed closeout and makes execution the condition of continued employment."
        }
      ],
      "availability": "Chapters 4, 9, 14, and 16, plus work-plot pressure throughout."
    },
    {
      "character_id": "mort_lazar",
      "age_at_story_start": 52,
      "physical_details": "Reading glasses on a chain, canvas apron, rough scarred hands, and a good wool coat reserved for serious days.",
      "key_relationships": {
        "nate_lazar": "son, unknown to him; knows him only as Dom",
        "linda_lazar": "wife and business partner",
        "gail_ruiz": "neighbor and ally",
        "dominic_altieri": "name on the notice letter and face Nate now wears"
      },
      "occupation_status": "Owner of Lazar's Hardware, Unit 7 at Eastbridge Plaza, tenant since 1989. After demolition he sells stock from his garage.",
      "aliases": [],
      "literacy_languages": "English. Deeply fluent in hardware and repair work.",
      "state_transitions": [
        {
          "chapter": "chapter_08",
          "change": "First real conversation with Dom at Gail's; explains the June notice letter."
        },
        {
          "chapter": "chapter_13",
          "change": "Lets Dom into the store and accepts the offer to ask around."
        },
        {
          "chapter": "chapter_17",
          "change": "Watches the store demolished."
        },
        {
          "chapter": "chapter_18",
          "change": "Runs the garage operation and begins the decline Nate remembers leading into March 2006."
        }
      ],
      "availability": "Seen in Chapters 3, 8, 13, 17, and 18."
    },
    {
      "character_id": "linda_lazar",
      "age_at_story_start": 50,
      "physical_details": "Small, practical, short-haired, usually carrying inventory or paperwork, often with a pencil behind one ear.",
      "key_relationships": {
        "mort_lazar": "wife, partner, and active watcher of his decline",
        "nate_lazar": "knows him only as Dom"
      },
      "occupation_status": "Co-owner, inventory manager, and bookkeeper for Lazar's Hardware; later helps run the garage setup.",
      "aliases": [],
      "literacy_languages": "English.",
      "state_transitions": [
        {
          "chapter": "chapter_13",
          "change": "Hears Dom promise to ask around and does not stop it."
        },
        {
          "chapter": "chapter_17",
          "change": "Cries at the demolition and stays physically close to Mort."
        },
        {
          "chapter": "chapter_18",
          "change": "Keeps the garage stock organized and stays within earshot of Mort."
        }
      ],
      "availability": "Background presence in Chapters 3, 13, 17, and 18."
    },
    {
      "character_id": "renata_altieri",
      "age_at_story_start": 58,
      "physical_details": "Short, solid, energetic, usually in an apron with flour somewhere on her arms.",
      "key_relationships": {
        "nate_lazar": "believes he is Dominic and reads him as calmer than before",
        "sarah_chen": "warm but complicated after the bakery fight",
        "tommy_altieri": "son and chronic worry"
      },
      "occupation_status": "Runs a Bridgeport bakery with very early hours.",
      "aliases": [
        "Ma"
      ],
      "literacy_languages": "English, some Italian.",
      "state_transitions": [
        {
          "chapter": "chapter_06",
          "change": "Reads Nate's altered behavior as a positive change in Dominic."
        },
        {
          "chapter": "chapter_18",
          "change": "Keeps Sunday family routine while damp weather starts bothering her knee."
        }
      ],
      "availability": "On-page in Chapters 6 and 18; active by phone and Sunday routine throughout."
    },
    {
      "character_id": "tommy_altieri",
      "age_at_story_start": 28,
      "physical_details": "Thinner and quicker than Dominic, with charm layered over panic; associated with a gold pinky ring and later a Saint Christopher medal.",
      "key_relationships": {
        "nate_lazar": "turns to him first for rescue money",
        "renata_altieri": "mother whose house he keeps endangering",
        "sarah_chen": "she reads his fear better than his performance"
      },
      "occupation_status": "Financially unstable gambler with vague day jobs and recurring debt trouble.",
      "aliases": [],
      "literacy_languages": "English.",
      "state_transitions": [
        {
          "chapter": "chapter_06",
          "change": "Asks for 1,500 dollars and gets 600."
        },
        {
          "chapter": "chapter_15",
          "change": "Debt rises to 4,000 dollars after violence behind O'Rourke's; Nate gives him 3,000."
        }
      ],
      "availability": "On-page in Chapters 6 and 15."
    },
    {
      "character_id": "ray_dunlap",
      "age_at_story_start": 33,
      "physical_details": "Tall, broad-shouldered, slightly soft, habitually tired, and fully built for office triage.",
      "key_relationships": {
        "nate_lazar": "coworker and strained friend",
        "victor_kassos": "boss whose judgment he tries not to test"
      },
      "occupation_status": "Project manager/developer at Kassos Development.",
      "aliases": [],
      "literacy_languages": "English. Fluent in permits, sequencing, and lender constraints.",
      "state_transitions": [
        {
          "chapter": "chapter_09",
          "change": "Loyalty strains after Nate's failed Eastbridge pitch."
        },
        {
          "chapter": "chapter_10",
          "change": "Catches Nate blanking on Stu Halpern and says he cannot cover that forever."
        },
        {
          "chapter": "chapter_14",
          "change": "Helps Nate sharpen a numbers-first pitch but warns him to let Victor's answer stand."
        }
      ],
      "availability": "Chapters 4, 9, 10, 14, and 16."
    },
    {
      "character_id": "gail_ruiz",
      "age_at_story_start": 54,
      "physical_details": "Fast, sturdy, mid-50s, hair pinned up, diner shoes flattened at the heel.",
      "key_relationships": {
        "nate_lazar": "lunch regular she knows as Dom",
        "mort_lazar": "neighbor and strip-mall ally"
      },
      "occupation_status": "Owner of Gail's Diner at Eastbridge Plaza; later reopens in a much smaller storefront two blocks west.",
      "aliases": [],
      "literacy_languages": "English, Spanish.",
      "state_transitions": [
        {
          "chapter": "chapter_08",
          "change": "Becomes Nate's regular lunch counter and bridge into the Eastbridge community."
        },
        {
          "chapter": "chapter_17",
          "change": "Walks away when the diner sign falls."
        },
        {
          "chapter": "chapter_18",
          "change": "Keeps the smaller diner alive through routine and carryover customers."
        }
      ],
      "availability": "Chapters 8, 17, and 18, plus off-page network presence."
    }
  ],
  "timeline": {
    "story_start": "July 11, 2005, 3:47 AM, in Dominic Altieri's apartment in Bridgeport, after a 2025 opening section in Nate's own apartment.",
    "estimated_span": "Roughly seven months on page: July 2005 through the first week of February 2006, with March 2006 still looming in Nate's memory as Mort's original-timeline death window.",
    "seasonal_track": [
      {
        "chapters": "1-6",
        "season": "Summer 2005: July into early August."
      },
      {
        "chapters": "7-10",
        "season": "Late summer to mid-fall 2005: August through October."
      },
      {
        "chapters": "11-15",
        "season": "Late fall to early winter 2005: late October through early December."
      },
      {
        "chapters": "16-18",
        "season": "Winter 2005-2006: mid-December through early February."
      }
    ],
    "key_events": [
      {
        "event": "Nate overwrites Dominic Altieri's body.",
        "timing": "July 11, 2005, 3:47 AM",
        "chapter": "chapter_01"
      },
      {
        "event": "Nate first sees Mort alive through Lazar's Hardware.",
        "timing": "July 13, 2005",
        "chapter": "chapter_03"
      },
      {
        "event": "Nate returns to Kassos and discovers Eastbridge is on Dominic's desk.",
        "timing": "Late July 2005",
        "chapter": "chapter_04"
      },
      {
        "event": "Nate and Sarah have sex for the first time after the overwrite.",
        "timing": "Early August 2005",
        "chapter": "chapter_05"
      },
      {
        "event": "Sunday dinner; Tommy asks for 1,500 dollars and gets 600.",
        "timing": "Early August 2005",
        "chapter": "chapter_06"
      },
      {
        "event": "Nate reads the full Eastbridge file and sees December 28 on paper.",
        "timing": "August 15, 2005",
        "chapter": "chapter_07"
      },
      {
        "event": "Mort sits beside Nate at Gail's and explains the June notice letter.",
        "timing": "Mid-September 2005",
        "chapter": "chapter_08"
      },
      {
        "event": "Victor dismantles Nate's first inside-the-company delay pitch.",
        "timing": "Late September 2005",
        "chapter": "chapter_09"
      },
      {
        "event": "Marco visit, Cape Cod failure, Stu Halpern blank, and the spiral notebook.",
        "timing": "October 2005",
        "chapter": "chapter_10"
      },
      {
        "event": "Nate discovers Dominic's March-June sent-mail chain opposing Eastbridge.",
        "timing": "Late October 2005",
        "chapter": "chapter_11"
      },
      {
        "event": "Sarah confronts Nate about the months-long pattern of wrongness.",
        "timing": "Late October 2005",
        "chapter": "chapter_12"
      },
      {
        "event": "Nate enters Lazar's Hardware, buys a level, and promises Mort he will ask around.",
        "timing": "First week of November 2005",
        "chapter": "chapter_13"
      },
      {
        "event": "Victor explains why full-clearance financing and politics have already locked Eastbridge.",
        "timing": "November 2005",
        "chapter": "chapter_14"
      },
      {
        "event": "Tommy's debt jumps to 4,000 dollars and Nate empties the remaining household cushion.",
        "timing": "Early December 2005",
        "chapter": "chapter_15"
      },
      {
        "event": "Nate signs the Eastbridge final closeout packet.",
        "timing": "December 19, 2005",
        "chapter": "chapter_16"
      },
      {
        "event": "Eastbridge Plaza is demolished.",
        "timing": "December 28, 2005",
        "chapter": "chapter_17"
      },
      {
        "event": "Gail reopens, Mort operates from the garage, and Nate starts routing small jobs to him.",
        "timing": "January to early February 2006",
        "chapter": "chapter_18"
      }
    ]
  },
  "geography": {
    "primary_setting": "Bridgeport, Connecticut, 2005-2006",
    "key_locations": [
      {
        "name": "Dominic and Sarah's apartment",
        "details": "One-bedroom mid-rise rental Dominic has occupied for nearly three years. Key continuity items: percolator, wall phone, Windows XP desktop, DVR, rattling summer AC, and overactive winter radiator."
      },
      {
        "name": "Kassos Development office",
        "details": "Second floor of a converted brick warehouse with an open bullpen, Victor's office, a conference room, and a plotter room."
      },
      {
        "name": "Eastbridge Plaza",
        "details": "Aging strip mall slated for mixed-use redevelopment: retail below apartments. Businesses named on-page are Nail Design by Kim, Park Cleaners, Gail's Diner, Al's Barbershop, Cesar's Market, and Lazar's Hardware."
      },
      {
        "name": "Lazar's Hardware",
        "details": "Unit 7 end unit, tenant site since 1989, known for the specialty fasteners wall and the faded hand-painted sign."
      },
      {
        "name": "Altieri family house",
        "details": "Small Bridgeport colonial with crowded family photos, a packed kitchen, and bakery spillover in the household routine."
      },
      {
        "name": "Gail's reopened diner",
        "details": "Smaller storefront two blocks west of the old plaza, with six stools and tighter booths."
      },
      {
        "name": "Mort's garage",
        "details": "Post-demolition sales space with salvaged shelves, labeled bins, a brass service bell, a space heater, and the old sign turned face-in."
      }
    ],
    "distances": [
      "Lazar's Hardware is the larger end unit at Eastbridge Plaza.",
      "Gail's Diner sat between Park Cleaners and Al's Barbershop in the old plaza.",
      "Gail's reopened diner is two blocks west of the former Eastbridge site.",
      "The Altieri house sits across Bridgeport from Dominic and Sarah's apartment."
    ]
  },
  "world_rules": [
    "The machine performs a consciousness-only overwrite on an occupied biological target; Dominic does not remain inside the body.",
    "Nate cannot simply go back to 2025 after Chapter 1.",
    "Nate keeps his own memories and gains none of Dominic's.",
    "Dominic's body retains practiced habits Nate does not consciously own: driving, signatures, kitchen movements, and reflexive intimacy.",
    "Fourteen-year-old Nate Lazar still exists elsewhere in Bridgeport in 2005.",
    "2005 constraints matter: no smartphones, no GPS, no cloud memory, and work life runs through landlines, flip phones, paper files, Windows XP, and Outlook."
  ],
  "power_structure": [
    {
      "holder": "Victor Kassos",
      "over": "Dominic/Nate, Ray, and the Kassos office",
      "mechanism": "Employment, file control, and paternalized discipline."
    },
    {
      "holder": "Victor Kassos, lenders, investors, and Councilman Dreher's network",
      "over": "Eastbridge Plaza and its tenants",
      "mechanism": "Full-clearance financing, investor commitments, year-end draws, rezoning approval, and the demolition package already committed on paper."
    },
    {
      "holder": "Councilman Dreher and Dreher Contracting",
      "over": "Rezoning and demolition execution",
      "mechanism": "Council approval plus the already-awarded demo package through Dreher's family network."
    },
    {
      "holder": "Tommy's gambling creditors",
      "over": "Tommy and, indirectly, Renata and Dominic",
      "mechanism": "Debt and intimidation."
    },
    {
      "holder": "Renata Altieri",
      "over": "Dominic/Nate and Tommy",
      "mechanism": "Maternal authority, food, guilt, and Sunday routine."
    },
    {
      "holder": "Sarah Chen",
      "over": "Nate's impersonation",
      "mechanism": "Years of intimate memory and domestic pattern recognition."
    }
  ],
  "objects": [
    {
      "name": "Vibe-coded machine",
      "owner": "Nate in 2025",
      "origin": "Built from AI-generated instructions, consumer electronics parts, and custom Python code.",
      "status": "Used in Chapter 1 and effectively gone after the overwrite.",
      "chapter_introduced": "chapter_01"
    },
    {
      "name": "Dominic's flip phone",
      "owner": "Dominic/Nate",
      "origin": "Standard 2005 mobile phone holding family and work routines.",
      "status": "Used throughout.",
      "chapter_introduced": "chapter_02"
    },
    {
      "name": "Dominic's wallet",
      "owner": "Dominic/Nate",
      "origin": "License, cards, membership card, and 43 dollars cash at first inventory.",
      "status": "Carried throughout; cash cushion elsewhere is gone by Chapter 15.",
      "chapter_introduced": "chapter_02"
    },
    {
      "name": "Rand McNally Connecticut road atlas",
      "owner": "Dominic/Nate",
      "origin": "Glove-compartment navigation for a pre-smartphone world.",
      "status": "Crucial early; later mostly symbolic.",
      "chapter_introduced": "chapter_03"
    },
    {
      "name": "Dominic's Honda Civic",
      "owner": "Dominic/Nate",
      "origin": "Daily car used for work, Eastbridge lunches, family visits, and demolition-day witness.",
      "status": "Active throughout.",
      "chapter_introduced": "chapter_03"
    },
    {
      "name": "Eastbridge Plaza project file",
      "owner": "Kassos Development",
      "origin": "Manila file with rent rolls, plans, permits, schedules, and tenant correspondence.",
      "status": "Lives on Dominic's desk until demolition is complete.",
      "chapter_introduced": "chapter_04"
    },
    {
      "name": "Morton's notice letter",
      "owner": "Eastbridge file copy",
      "origin": "June 8, 2005 tenant notice to Morton Lazar, signed in blue ink by Dominic Altieri.",
      "status": "Nate repeatedly re-reads it.",
      "chapter_introduced": "chapter_07"
    },
    {
      "name": "Spiral notebook dossier",
      "owner": "Nate",
      "origin": "Cheap pharmacy notebook cataloging Dominic's family, friends, work, trips, and mistakes.",
      "status": "Active from Chapter 10 onward.",
      "chapter_introduced": "chapter_10"
    },
    {
      "name": "Dominic's Eastbridge sent-mail chain",
      "owner": "Dominic's Outlook account",
      "origin": "March-June 2005 emails arguing for phased demolition, relocation help, and more time for named tenants.",
      "status": "Discovered in Chapter 11 and proves Dominic fought the project internally.",
      "chapter_introduced": "chapter_11"
    },
    {
      "name": "Twenty-four-inch level",
      "owner": "Nate",
      "origin": "Bought in person from Lazar's Hardware for Sarah's crooked shelf.",
      "status": "Kept in the closet as a reminder of the promise to Mort.",
      "chapter_introduced": "chapter_13"
    },
    {
      "name": "Eastbridge final site closeout packet",
      "owner": "Kassos Development / Victor Kassos",
      "origin": "Packet containing site photos, utility disconnects, contractor release, and signature page.",
      "status": "Signed by Nate as Dominic in Chapter 16.",
      "chapter_introduced": "chapter_16"
    },
    {
      "name": "Left-hand threaded machine screw",
      "owner": "Nate",
      "origin": "Recovered from the Lazar's Hardware rubble; the kind of odd stock Mort kept when other stores stopped bothering.",
      "status": "Pocketed after demolition.",
      "chapter_introduced": "chapter_17"
    }
  ],
  "financial_state": {
    "debts": [
      {
        "creditor": "Tommy's gambling creditors",
        "amount": "4,000 dollars total in Chapter 15",
        "deadline": "One week after the O'Rourke's assault",
        "status": "Nate pays 3,000 dollars from Dominic's checking and savings; Tommy says more is still owed."
      }
    ],
    "income_sources": [
      {
        "source": "Dominic's salary at Kassos Development",
        "amount": "Unspecified mid-level development salary",
        "reliability": "Active but threatened if Nate stops executing."
      },
      {
        "source": "Sarah Chen's teaching salary",
        "amount": "Unspecified",
        "reliability": "Stable enough to cover groceries and the electric for a while after Chapter 15."
      },
      {
        "source": "Dominic's checking and savings balances",
        "amount": "2,200 dollars checking plus 800 dollars savings before Chapter 15; zero after Tommy's 3,000-dollar check clears",
        "reliability": "Depleted."
      },
      {
        "source": "Mort's garage sales",
        "amount": "Small cash sales of leftover stock",
        "reliability": "Minimal and inconsistent."
      }
    ]
  },
  "knowledge_state": [
    {
      "character": "nate_lazar",
      "knows": "He overwrote Dominic and cannot simply go back to 2025.",
      "learned_in": "chapter_01",
      "hidden_from": "Everyone else."
    },
    {
      "character": "nate_lazar",
      "knows": "In the original timeline Mort is dead by March 2006, so the garage period is a countdown.",
      "learned_in": "chapter_01 (pre-story knowledge from 2025)",
      "hidden_from": "Everyone else."
    },
    {
      "character": "nate_lazar",
      "knows": "Eastbridge demolition is scheduled for December 28, 2005 and already broken into administrative steps.",
      "learned_in": "chapter_07",
      "hidden_from": "His personal stake in it."
    },
    {
      "character": "nate_lazar",
      "knows": "Dominic spent March-June 2005 proposing delayed notices, relocation help, and phase-one preservation for Mort, Gail, and Mrs. Park.",
      "learned_in": "chapter_11",
      "hidden_from": "Sarah, Mort, Linda, Gail, Tommy, and Renata."
    },
    {
      "character": "nate_lazar",
      "knows": "Eastbridge is locked by full-clearance equity, lenders, investors, Dreher's network, year-end draws, and the already-awarded demo package.",
      "learned_in": "chapter_14",
      "hidden_from": "Tenants and the public."
    },
    {
      "character": "sarah_chen",
      "knows": "The man in her apartment has been fundamentally wrong since July: missing kitchen memory, missing shared history, altered habits, and a pause before hearing 'Dom'.",
      "learned_in": "chapters 5-12",
      "hidden_from": "She still does not know the cause."
    },
    {
      "character": "ray_dunlap",
      "knows": "Dominic is missing client and file knowledge he should know cold and may be drifting toward a breakdown.",
      "learned_in": "chapters 9-10",
      "hidden_from": "Ray reports enough upward to protect the project, but not a cause he does not know."
    },
    {
      "character": "mort_lazar",
      "knows": "A man named Dom who works in real estate drank coffee at Gail's, entered the store, and promised to ask around about the redevelopment.",
      "learned_in": "chapters 8 and 13",
      "hidden_from": "Mort does not know Dom is Nate or that Dom is the Dominic Altieri on the notice letter."
    },
    {
      "character": "linda_lazar",
      "knows": "By Chapter 18, Dom from real estate is quietly steering odd jobs and customers toward Mort's garage operation.",
      "learned_in": "chapter_18",
      "hidden_from": "Linda does not know Dom is Nate or why he is helping."
    },
    {
      "character": "victor_kassos",
      "knows": "Dominic pushed back on Eastbridge in spring 2005 and, after Nate's arrival, has been getting personally entangled with Eastbridge tenants again.",
      "learned_in": "spring 2005 and chapter_14",
      "hidden_from": "Victor does not know why Dominic changed."
    }
  ],
  "environmental_constants": [
    "Bridgeport summer is humid, sticky, and window-unit loud.",
    "Lazar's Hardware smells of sawdust, cold metal, WD-40, and rubber mats.",
    "Gail's Diner is coffee boiled too long, fryer grease, a tired bell, and a counter worn smooth by elbows.",
    "Kassos Development is fluorescent hum, carpet tile, stale coffee, desktop fans, and paper everywhere.",
    "The Altieri house is garlic, pork fat, bread, espresso, box fans, and too many family photos.",
    "Dominic and Sarah's apartment has a rattling summer AC and clanking winter radiators.",
    "After demolition, the old Eastbridge site becomes chain-link, green mesh, diesel, wet concrete, and a permit trailer.",
    "Mort's garage smells of cold metal, damp cardboard, space-heater dust, and cooling coffee."
  ]
}
