{
  "batch_count": 5,
  "batch_index": 5,
  "brief": "",
  "candidate_count": 6,
  "candidates": [
    {
      "active_axes": [
        {
          "axis": "embodied_labor_specificity",
          "label": "embodied labor specificity",
          "value": 0.995
        },
        {
          "axis": "life_stage_skew",
          "label": "life-stage skew",
          "value": 0.933
        },
        {
          "axis": "romantic_centrality",
          "label": "romantic centrality",
          "value": 0.861
        },
        {
          "axis": "mobility_migration",
          "label": "mobility and migration",
          "value": 0.848
        },
        {
          "axis": "ontological_instability",
          "label": "ontological instability",
          "value": 0.83
        },
        {
          "axis": "ecological_biome_specificity",
          "label": "ecological and biome specificity",
          "value": 0.828
        }
      ],
      "candidate_id": "candidate_25",
      "kind": "independent",
      "risk_gloss": "high moral contamination and transgression, high bodily explicitness, high messiness and anti-sanitization, low violence proximity, muted profanity tolerance",
      "risk_overlay": {
        "bodily_explicitness": 0.71,
        "messiness_anti_sanitization": 0.702,
        "moral_contamination_transgression": 0.737,
        "profanity_tolerance": 0.56,
        "violence_proximity": 0.151
      },
      "suppressed_axes": [
        {
          "axis": "tragic_gravity",
          "label": "tragic gravity",
          "value": 0.076
        },
        {
          "axis": "external_event_pressure",
          "label": "external event pressure",
          "value": 0.098
        },
        {
          "axis": "satiric_bite",
          "label": "satiric bite",
          "value": 0.142
        }
      ],
      "vector": {
        "class_economic_pressure": 0.687,
        "comic_energy": 0.757,
        "communal_entanglement": 0.582,
        "documentality_legibility": 0.175,
        "ecological_biome_specificity": 0.828,
        "embodied_labor_specificity": 0.995,
        "epistemic_uncertainty": 0.237,
        "erotic_charge": 0.791,
        "external_event_pressure": 0.098,
        "family_entanglement": 0.414,
        "fantasy_mythic_pressure": 0.18,
        "historical_embeddedness": 0.363,
        "institutional_density": 0.142,
        "life_stage_skew": 0.933,
        "mobility_migration": 0.848,
        "obsession_compulsion": 0.747,
        "ontological_instability": 0.83,
        "procedurality": 0.147,
        "protagonist_plurality": 0.208,
        "psychological_interiority": 0.413,
        "public_civic_scale": 0.146,
        "romantic_centrality": 0.861,
        "satiric_bite": 0.142,
        "science_technology_pressure": 0.778,
        "secrecy_deception": 0.394,
        "spiritual_metaphysical_pressure": 0.435,
        "tenderness": 0.803,
        "time_span": 0.287,
        "tragic_gravity": 0.076,
        "worldbuilding_density": 0.546
      },
      "vector_gloss": "very high embodied labor specificity, very high life-stage skew, very high romantic centrality, high mobility and migration, very low tragic gravity, very low external event pressure"
    },
    {
      "active_axes": [
        {
          "axis": "tenderness",
          "label": "tenderness",
          "value": 0.996
        },
        {
          "axis": "communal_entanglement",
          "label": "communal entanglement",
          "value": 0.955
        },
        {
          "axis": "obsession_compulsion",
          "label": "obsession and compulsion",
          "value": 0.911
        },
        {
          "axis": "class_economic_pressure",
          "label": "class and economic pressure",
          "value": 0.848
        },
        {
          "axis": "comic_energy",
          "label": "comic energy",
          "value": 0.842
        },
        {
          "axis": "satiric_bite",
          "label": "satiric bite",
          "value": 0.837
        }
      ],
      "candidate_id": "candidate_26",
      "kind": "independent",
      "risk_gloss": "very high messiness and anti-sanitization, high moral contamination and transgression, present profanity tolerance, low bodily explicitness, low violence proximity",
      "risk_overlay": {
        "bodily_explicitness": 0.122,
        "messiness_anti_sanitization": 0.988,
        "moral_contamination_transgression": 0.686,
        "profanity_tolerance": 0.182,
        "violence_proximity": 0.13
      },
      "suppressed_axes": [
        {
          "axis": "science_technology_pressure",
          "label": "science and technology pressure",
          "value": 0.05
        },
        {
          "axis": "external_event_pressure",
          "label": "external event pressure",
          "value": 0.072
        },
        {
          "axis": "epistemic_uncertainty",
          "label": "contested knowledge and unstable truth",
          "value": 0.079
        }
      ],
      "vector": {
        "class_economic_pressure": 0.848,
        "comic_energy": 0.842,
        "communal_entanglement": 0.955,
        "documentality_legibility": 0.606,
        "ecological_biome_specificity": 0.14,
        "embodied_labor_specificity": 0.495,
        "epistemic_uncertainty": 0.079,
        "erotic_charge": 0.189,
        "external_event_pressure": 0.072,
        "family_entanglement": 0.775,
        "fantasy_mythic_pressure": 0.785,
        "historical_embeddedness": 0.306,
        "institutional_density": 0.269,
        "life_stage_skew": 0.473,
        "mobility_migration": 0.39,
        "obsession_compulsion": 0.911,
        "ontological_instability": 0.543,
        "procedurality": 0.088,
        "protagonist_plurality": 0.665,
        "psychological_interiority": 0.688,
        "public_civic_scale": 0.615,
        "romantic_centrality": 0.669,
        "satiric_bite": 0.837,
        "science_technology_pressure": 0.05,
        "secrecy_deception": 0.542,
        "spiritual_metaphysical_pressure": 0.228,
        "tenderness": 0.996,
        "time_span": 0.763,
        "tragic_gravity": 0.609,
        "worldbuilding_density": 0.782
      },
      "vector_gloss": "very high tenderness, very high communal entanglement, very high obsession and compulsion, high class and economic pressure, very low science and technology pressure, very low external event pressure"
    },
    {
      "active_axes": [
        {
          "axis": "family_entanglement",
          "label": "family entanglement",
          "value": 0.985
        },
        {
          "axis": "tragic_gravity",
          "label": "tragic gravity",
          "value": 0.966
        },
        {
          "axis": "ecological_biome_specificity",
          "label": "ecological and biome specificity",
          "value": 0.956
        },
        {
          "axis": "mobility_migration",
          "label": "mobility and migration",
          "value": 0.917
        },
        {
          "axis": "external_event_pressure",
          "label": "external event pressure",
          "value": 0.891
        },
        {
          "axis": "spiritual_metaphysical_pressure",
          "label": "spiritual and metaphysical pressure",
          "value": 0.837
        }
      ],
      "candidate_id": "candidate_27",
      "kind": "independent",
      "risk_gloss": "very high violence proximity, high bodily explicitness, high moral contamination and transgression, very low profanity tolerance, low messiness and anti-sanitization",
      "risk_overlay": {
        "bodily_explicitness": 0.817,
        "messiness_anti_sanitization": 0.238,
        "moral_contamination_transgression": 0.749,
        "profanity_tolerance": 0.062,
        "violence_proximity": 0.998
      },
      "suppressed_axes": [
        {
          "axis": "institutional_density",
          "label": "rule-bound collective life",
          "value": 0.091
        },
        {
          "axis": "fantasy_mythic_pressure",
          "label": "fantasy and mythic pressure",
          "value": 0.1
        },
        {
          "axis": "ontological_instability",
          "label": "ontological instability",
          "value": 0.124
        }
      ],
      "vector": {
        "class_economic_pressure": 0.602,
        "comic_energy": 0.463,
        "communal_entanglement": 0.701,
        "documentality_legibility": 0.666,
        "ecological_biome_specificity": 0.956,
        "embodied_labor_specificity": 0.797,
        "epistemic_uncertainty": 0.674,
        "erotic_charge": 0.436,
        "external_event_pressure": 0.891,
        "family_entanglement": 0.985,
        "fantasy_mythic_pressure": 0.1,
        "historical_embeddedness": 0.172,
        "institutional_density": 0.091,
        "life_stage_skew": 0.808,
        "mobility_migration": 0.917,
        "obsession_compulsion": 0.745,
        "ontological_instability": 0.124,
        "procedurality": 0.334,
        "protagonist_plurality": 0.272,
        "psychological_interiority": 0.166,
        "public_civic_scale": 0.678,
        "romantic_centrality": 0.568,
        "satiric_bite": 0.242,
        "science_technology_pressure": 0.678,
        "secrecy_deception": 0.355,
        "spiritual_metaphysical_pressure": 0.837,
        "tenderness": 0.236,
        "time_span": 0.8,
        "tragic_gravity": 0.966,
        "worldbuilding_density": 0.282
      },
      "vector_gloss": "very high family entanglement, very high tragic gravity, very high ecological and biome specificity, very high mobility and migration, very low rule-bound collective life, very low fantasy and mythic pressure"
    },
    {
      "active_axes": [
        {
          "axis": "science_technology_pressure",
          "label": "science and technology pressure",
          "value": 0.97
        },
        {
          "axis": "public_civic_scale",
          "label": "shared social consequence",
          "value": 0.931
        },
        {
          "axis": "spiritual_metaphysical_pressure",
          "label": "spiritual and metaphysical pressure",
          "value": 0.858
        },
        {
          "axis": "protagonist_plurality",
          "label": "protagonist plurality",
          "value": 0.817
        },
        {
          "axis": "erotic_charge",
          "label": "erotic charge",
          "value": 0.816
        },
        {
          "axis": "institutional_density",
          "label": "rule-bound collective life",
          "value": 0.815
        }
      ],
      "candidate_id": "candidate_28",
      "kind": "independent",
      "risk_gloss": "very high profanity tolerance, very high violence proximity, high moral contamination and transgression, very low bodily explicitness, very low messiness and anti-sanitization",
      "risk_overlay": {
        "bodily_explicitness": 0.022,
        "messiness_anti_sanitization": 0.103,
        "moral_contamination_transgression": 0.818,
        "profanity_tolerance": 0.948,
        "violence_proximity": 0.876
      },
      "suppressed_axes": [
        {
          "axis": "worldbuilding_density",
          "label": "worldbuilding density",
          "value": 0.01
        },
        {
          "axis": "psychological_interiority",
          "label": "psychological interiority",
          "value": 0.068
        },
        {
          "axis": "family_entanglement",
          "label": "family entanglement",
          "value": 0.086
        }
      ],
      "vector": {
        "class_economic_pressure": 0.404,
        "comic_energy": 0.59,
        "communal_entanglement": 0.711,
        "documentality_legibility": 0.27,
        "ecological_biome_specificity": 0.51,
        "embodied_labor_specificity": 0.384,
        "epistemic_uncertainty": 0.164,
        "erotic_charge": 0.816,
        "external_event_pressure": 0.722,
        "family_entanglement": 0.086,
        "fantasy_mythic_pressure": 0.744,
        "historical_embeddedness": 0.414,
        "institutional_density": 0.815,
        "life_stage_skew": 0.81,
        "mobility_migration": 0.206,
        "obsession_compulsion": 0.381,
        "ontological_instability": 0.393,
        "procedurality": 0.752,
        "protagonist_plurality": 0.817,
        "psychological_interiority": 0.068,
        "public_civic_scale": 0.931,
        "romantic_centrality": 0.178,
        "satiric_bite": 0.477,
        "science_technology_pressure": 0.97,
        "secrecy_deception": 0.627,
        "spiritual_metaphysical_pressure": 0.858,
        "tenderness": 0.346,
        "time_span": 0.396,
        "tragic_gravity": 0.607,
        "worldbuilding_density": 0.01
      },
      "vector_gloss": "very high science and technology pressure, very high shared social consequence, very high spiritual and metaphysical pressure, high protagonist plurality, very low worldbuilding density, very low psychological interiority"
    },
    {
      "active_axes": [
        {
          "axis": "satiric_bite",
          "label": "satiric bite",
          "value": 0.936
        },
        {
          "axis": "life_stage_skew",
          "label": "life-stage skew",
          "value": 0.925
        },
        {
          "axis": "procedurality",
          "label": "stepwise task pressure",
          "value": 0.919
        },
        {
          "axis": "time_span",
          "label": "long time-span pressure",
          "value": 0.827
        },
        {
          "axis": "public_civic_scale",
          "label": "shared social consequence",
          "value": 0.751
        },
        {
          "axis": "external_event_pressure",
          "label": "external event pressure",
          "value": 0.721
        }
      ],
      "candidate_id": "candidate_29",
      "kind": "independent",
      "risk_gloss": "high violence proximity, high moral contamination and transgression, high bodily explicitness, very low profanity tolerance, low messiness and anti-sanitization",
      "risk_overlay": {
        "bodily_explicitness": 0.687,
        "messiness_anti_sanitization": 0.197,
        "moral_contamination_transgression": 0.762,
        "profanity_tolerance": 0.075,
        "violence_proximity": 0.845
      },
      "suppressed_axes": [
        {
          "axis": "ontological_instability",
          "label": "ontological instability",
          "value": 0.041
        },
        {
          "axis": "institutional_density",
          "label": "rule-bound collective life",
          "value": 0.086
        },
        {
          "axis": "documentality_legibility",
          "label": "formal recognition, naming, and social legibility",
          "value": 0.136
        }
      ],
      "vector": {
        "class_economic_pressure": 0.48,
        "comic_energy": 0.152,
        "communal_entanglement": 0.559,
        "documentality_legibility": 0.136,
        "ecological_biome_specificity": 0.183,
        "embodied_labor_specificity": 0.672,
        "epistemic_uncertainty": 0.385,
        "erotic_charge": 0.207,
        "external_event_pressure": 0.721,
        "family_entanglement": 0.693,
        "fantasy_mythic_pressure": 0.281,
        "historical_embeddedness": 0.417,
        "institutional_density": 0.086,
        "life_stage_skew": 0.925,
        "mobility_migration": 0.177,
        "obsession_compulsion": 0.232,
        "ontological_instability": 0.041,
        "procedurality": 0.919,
        "protagonist_plurality": 0.679,
        "psychological_interiority": 0.656,
        "public_civic_scale": 0.751,
        "romantic_centrality": 0.14,
        "satiric_bite": 0.936,
        "science_technology_pressure": 0.389,
        "secrecy_deception": 0.299,
        "spiritual_metaphysical_pressure": 0.634,
        "tenderness": 0.565,
        "time_span": 0.827,
        "tragic_gravity": 0.201,
        "worldbuilding_density": 0.253
      },
      "vector_gloss": "very high satiric bite, very high life-stage skew, very high stepwise task pressure, high long time-span pressure, very low ontological instability, very low rule-bound collective life"
    },
    {
      "active_axes": [
        {
          "axis": "comic_energy",
          "label": "comic energy",
          "value": 0.994
        },
        {
          "axis": "science_technology_pressure",
          "label": "science and technology pressure",
          "value": 0.968
        },
        {
          "axis": "documentality_legibility",
          "label": "formal recognition, naming, and social legibility",
          "value": 0.924
        },
        {
          "axis": "worldbuilding_density",
          "label": "worldbuilding density",
          "value": 0.909
        },
        {
          "axis": "epistemic_uncertainty",
          "label": "contested knowledge and unstable truth",
          "value": 0.805
        },
        {
          "axis": "public_civic_scale",
          "label": "shared social consequence",
          "value": 0.788
        }
      ],
      "candidate_id": "candidate_30",
      "kind": "independent",
      "risk_gloss": "very high profanity tolerance, moderate-high bodily explicitness, moderate-high messiness and anti-sanitization, very low violence proximity, low moral contamination and transgression",
      "risk_overlay": {
        "bodily_explicitness": 0.654,
        "messiness_anti_sanitization": 0.6,
        "moral_contamination_transgression": 0.255,
        "profanity_tolerance": 0.887,
        "violence_proximity": 0.113
      },
      "suppressed_axes": [
        {
          "axis": "obsession_compulsion",
          "label": "obsession and compulsion",
          "value": 0.011
        },
        {
          "axis": "life_stage_skew",
          "label": "life-stage skew",
          "value": 0.016
        },
        {
          "axis": "institutional_density",
          "label": "rule-bound collective life",
          "value": 0.067
        }
      ],
      "vector": {
        "class_economic_pressure": 0.641,
        "comic_energy": 0.994,
        "communal_entanglement": 0.692,
        "documentality_legibility": 0.924,
        "ecological_biome_specificity": 0.695,
        "embodied_labor_specificity": 0.536,
        "epistemic_uncertainty": 0.805,
        "erotic_charge": 0.612,
        "external_event_pressure": 0.506,
        "family_entanglement": 0.565,
        "fantasy_mythic_pressure": 0.074,
        "historical_embeddedness": 0.771,
        "institutional_density": 0.067,
        "life_stage_skew": 0.016,
        "mobility_migration": 0.164,
        "obsession_compulsion": 0.011,
        "ontological_instability": 0.209,
        "procedurality": 0.529,
        "protagonist_plurality": 0.491,
        "psychological_interiority": 0.604,
        "public_civic_scale": 0.788,
        "romantic_centrality": 0.555,
        "satiric_bite": 0.56,
        "science_technology_pressure": 0.968,
        "secrecy_deception": 0.616,
        "spiritual_metaphysical_pressure": 0.256,
        "tenderness": 0.461,
        "time_span": 0.478,
        "tragic_gravity": 0.327,
        "worldbuilding_density": 0.909
      },
      "vector_gloss": "very high comic energy, very high science and technology pressure, very high formal recognition, naming, and social legibility, very high worldbuilding density, very low obsession and compulsion, very low life-stage skew"
    }
  ],
  "core_axes": [
    {
      "label": "comic energy",
      "name": "comic_energy"
    },
    {
      "label": "tragic gravity",
      "name": "tragic_gravity"
    },
    {
      "label": "satiric bite",
      "name": "satiric_bite"
    },
    {
      "label": "tenderness",
      "name": "tenderness"
    },
    {
      "label": "erotic charge",
      "name": "erotic_charge"
    },
    {
      "label": "psychological interiority",
      "name": "psychological_interiority"
    },
    {
      "label": "external event pressure",
      "name": "external_event_pressure"
    },
    {
      "label": "procedurality",
      "name": "procedurality"
    },
    {
      "label": "secrecy and deception",
      "name": "secrecy_deception"
    },
    {
      "label": "obsession and compulsion",
      "name": "obsession_compulsion"
    },
    {
      "label": "epistemic uncertainty",
      "name": "epistemic_uncertainty"
    },
    {
      "label": "long time-span pressure",
      "name": "time_span"
    },
    {
      "label": "protagonist plurality",
      "name": "protagonist_plurality"
    },
    {
      "label": "life-stage skew",
      "name": "life_stage_skew"
    },
    {
      "label": "romantic centrality",
      "name": "romantic_centrality"
    },
    {
      "label": "family entanglement",
      "name": "family_entanglement"
    },
    {
      "label": "communal entanglement",
      "name": "communal_entanglement"
    },
    {
      "label": "public-civic scale",
      "name": "public_civic_scale"
    },
    {
      "label": "institutional density",
      "name": "institutional_density"
    },
    {
      "label": "class and economic pressure",
      "name": "class_economic_pressure"
    },
    {
      "label": "embodied labor specificity",
      "name": "embodied_labor_specificity"
    },
    {
      "label": "documentality and legibility",
      "name": "documentality_legibility"
    },
    {
      "label": "ecological and biome specificity",
      "name": "ecological_biome_specificity"
    },
    {
      "label": "mobility and migration",
      "name": "mobility_migration"
    },
    {
      "label": "historical embeddedness",
      "name": "historical_embeddedness"
    },
    {
      "label": "worldbuilding density",
      "name": "worldbuilding_density"
    },
    {
      "label": "fantasy and mythic pressure",
      "name": "fantasy_mythic_pressure"
    },
    {
      "label": "science and technology pressure",
      "name": "science_technology_pressure"
    },
    {
      "label": "spiritual and metaphysical pressure",
      "name": "spiritual_metaphysical_pressure"
    },
    {
      "label": "ontological instability",
      "name": "ontological_instability"
    }
  ],
  "derived_seed": "091484e48109b23cc99336cc90d77dce",
  "field_centroid": {
    "class_economic_pressure": 0.541,
    "comic_energy": 0.448,
    "communal_entanglement": 0.538,
    "documentality_legibility": 0.514,
    "ecological_biome_specificity": 0.529,
    "embodied_labor_specificity": 0.543,
    "epistemic_uncertainty": 0.509,
    "erotic_charge": 0.42,
    "external_event_pressure": 0.532,
    "family_entanglement": 0.535,
    "fantasy_mythic_pressure": 0.475,
    "historical_embeddedness": 0.506,
    "institutional_density": 0.487,
    "life_stage_skew": 0.559,
    "mobility_migration": 0.484,
    "obsession_compulsion": 0.562,
    "ontological_instability": 0.506,
    "procedurality": 0.492,
    "protagonist_plurality": 0.495,
    "psychological_interiority": 0.501,
    "public_civic_scale": 0.538,
    "romantic_centrality": 0.448,
    "satiric_bite": 0.547,
    "science_technology_pressure": 0.526,
    "secrecy_deception": 0.511,
    "spiritual_metaphysical_pressure": 0.522,
    "tenderness": 0.554,
    "time_span": 0.539,
    "tragic_gravity": 0.515,
    "worldbuilding_density": 0.46
  },
  "field_gloss": "Field built from independently sampled vectors selected for spread. Recurring strong axes include ecological and biome specificity, science and technology pressure, comic energy, formal recognition, naming, and social legibility. Recurring muted axes include rule-bound collective life, erotic charge.",
  "field_risk_centroid": {
    "bodily_explicitness": 0.487,
    "messiness_anti_sanitization": 0.549,
    "moral_contamination_transgression": 0.531,
    "profanity_tolerance": 0.534,
    "violence_proximity": 0.452
  },
  "field_risk_gloss": "present messiness and anti-sanitization, present profanity tolerance, present moral contamination and transgression, muted violence proximity, muted bodily explicitness",
  "generation_batch_size": 6,
  "legacy_resume": false,
  "min_unique_clusters": 8,
  "prior_batch_repetition_warning": "Earlier batches already established some concrete engines. Do not solve the current batch by lightly re-skinning the same verification, gatekeeping, or record-management scaffold.",
  "reroll_index": 0,
  "risk_axes": [
    {
      "label": "messiness and anti-sanitization",
      "name": "messiness_anti_sanitization"
    },
    {
      "label": "profanity tolerance",
      "name": "profanity_tolerance"
    },
    {
      "label": "bodily explicitness",
      "name": "bodily_explicitness"
    },
    {
      "label": "violence proximity",
      "name": "violence_proximity"
    },
    {
      "label": "moral contamination and transgression",
      "name": "moral_contamination_transgression"
    }
  ],
  "schema_version": 4,
  "search_rubric": {
    "award_agnostic": true,
    "criteria": [
      "long-book viability",
      "range of scene textures",
      "character and relational leverage",
      "pressure that can mutate over time",
      "world or place specificity",
      "originality without gimmickry",
      "aesthetic-risk headroom"
    ]
  },
  "search_strategy": "independent_spread_vectors",
  "seed": "091484e48109b23cc99336cc90d77dce",
  "shortlist_size": 6
}
